wappstore/__init__.py
wappstore/data/README.md
wappstore/data/__init__.py
wappstore/data/crud.py
wappstore/data/database.py
wappstore/data/models.py
wappstore/data/seeding.py
wappstore/input.css
wappstore/main.py
wappstore/models.py
wappstore/static/output.css
wappstore/templates/apps/detail.html
wappstore/templates/apps/index.html
wappstore/templates/apps/new.html
wappstore/url.py
wappstore/webmanifest.py
wappstore-1.0.1.dist-info/LICENSE
wappstore-1.0.1.dist-info/METADATA
wappstore-1.0.1.dist-info/WHEEL
wappstore-1.0.1.dist-info/RECORD
