Metadata-Version: 2.1
Name: wappstore
Version: 1.0.1
Summary: Improve Web App discoverability
Home-page: https://github.com/SantaClaas/wApp
License: Apache-2.0
Author: Claas
Author-email: claas.moehlmann@outlook.com
Requires-Python: >=3.11,<4.0
Classifier: License :: OSI Approved :: Apache Software License
Classifier: Programming Language :: Python :: 3
Classifier: Programming Language :: Python :: 3.11
Requires-Dist: fastapi (>=0.96.0,<0.97.0)
Requires-Dist: httpx (>=0.24.1,<0.25.0)
Requires-Dist: jinja2 (>=3.1.2,<4.0.0)
Requires-Dist: marshmallow (>=3.19.0,<4.0.0)
Requires-Dist: python-multipart (>=0.0.6,<0.0.7)
Requires-Dist: sqlalchemy (>=2.0.15,<3.0.0)
Requires-Dist: uvicorn (>=0.22.0,<0.23.0)
Project-URL: Repository, https://github.com/SantaClaas/wApp
